coplay_mcp_server/__init__.py
coplay_mcp_server/code_generator.py
coplay_mcp_server/image_utils.py
coplay_mcp_server/process_discovery.py
coplay_mcp_server/server.py
coplay_mcp_server/unity_client.py
coplay_mcp_server/generated_tools/.gitignore
coplay_mcp_server/generated_tools/__init__.py
coplay_mcp_server/generated_tools/agent_tool_tools.py
coplay_mcp_server/generated_tools/asset_functions_tools.py
coplay_mcp_server/generated_tools/image_tool_tools.py
coplay_mcp_server/generated_tools/input_action_tool_tools.py
coplay_mcp_server/generated_tools/package_tool_tools.py
coplay_mcp_server/generated_tools/profiler_functions_tools.py
coplay_mcp_server/generated_tools/scene_view_functions_tools.py
coplay_mcp_server/generated_tools/screenshot_tool_tools.py
coplay_mcp_server/generated_tools/ui_functions_tools.py
coplay_mcp_server/generated_tools/unity_functions_tools.py
coplay_mcp_server-1.5.1.dist-info/METADATA
coplay_mcp_server-1.5.1.dist-info/WHEEL
coplay_mcp_server-1.5.1.dist-info/entry_points.txt
coplay_mcp_server-1.5.1.dist-info/licenses/LICENSE
coplay_mcp_server-1.5.1.dist-info/RECORD
