Metadata-Version: 2.4
Name: coplay-mcp-server
Version: 1.5.1
Summary: A Model Context Protocol (MCP) server for Coplay, providing Unity integration capabilities
Project-URL: Homepage, https://coplay.dev/
Project-URL: Repository, https://github.com/CoplayDev/coplay-unity-plugin
Project-URL: Documentation, https://docs.coplay.dev/
Project-URL: Issues, https://github.com/CoplayDev/coplay-unity-plugin/issues
Author-email: Coplay Dev <dev@coplay.com>
Maintainer-email: Coplay Dev <dev@coplay.com>
License: MIT
License-File: LICENSE
Keywords: coplay,mcp,model-context-protocol,unity,unity-editor
Classifier: Development Status :: 4 - Beta
Classifier: Intended Audience :: Developers
Classifier: License :: OSI Approved :: MIT License
Classifier: Operating System :: OS Independent
Classifier: Programming Language :: Python :: 3
Classifier: Programming Language :: Python :: 3.11
Classifier: Topic :: Games/Entertainment
Classifier: Topic :: Software Development :: Libraries :: Python Modules
Requires-Python: >=3.11
Requires-Dist: aiofiles>=24.1.0
Requires-Dist: anyio>=4.10.0
Requires-Dist: fastmcp>=2.0.0
Requires-Dist: psutil>=7.0.0
Requires-Dist: pydantic>=2.11.7
Requires-Dist: watchdog>=6.0.0
